{
    "lesson_id": "eiken-pre2-3",
    "title": "Lesson 3",
    "paragraph": "Food and drink bring variety to our meals and social occasions. Ingredients like vegetables, meat, and seasonings are combined by chefs to create soups, desserts and main dishes. Healthy choices and balanced portions help you enjoy food while staying fit.",
    "words": [
      { "word": "beef", "meaning": "meat from cattle", "japaneseMeaning": "牛肉", "synonyms": "steak, meat", "antonyms": "vegetarian, tofu", "example": "She ordered a beef steak for dinner." },
      { "word": "cabbage", "meaning": "a leafy vegetable used in many dishes", "japaneseMeaning": "キャベツ", "synonyms": "greens, brassica", "antonyms": "", "example": "Cabbage is common in salads and stir-fries." },
      { "word": "carrot", "meaning": "an orange root vegetable", "japaneseMeaning": "にんじん", "synonyms": "root vegetable", "antonyms": "", "example": "He chopped a carrot for the soup." },
      { "word": "cereal", "meaning": "grains eaten for breakfast", "japaneseMeaning": "シリアル", "synonyms": "grain, breakfast food", "antonyms": "sweets", "example": "She poured milk over the cereal." },
      { "word": "chef", "meaning": "a professional cook", "japaneseMeaning": "シェフ", "synonyms": "cook, culinary artist", "antonyms": "diner, customer", "example": "The chef prepared a special menu." },
      { "word": "dessert", "meaning": "a sweet course served at the end of a meal", "japaneseMeaning": "デザート", "synonyms": "sweet, pudding", "antonyms": "main course, appetizer", "example": "We had ice cream for dessert." },
      { "word": "flour", "meaning": "a powder made from ground grains used for baking", "japaneseMeaning": "小麦粉", "synonyms": "meal, powder", "antonyms": "", "example": "Add flour to make the dough." },
      { "word": "garlic", "meaning": "a strong-flavored bulb used in cooking", "japaneseMeaning": "にんにく", "synonyms": "allium, seasoning", "antonyms": "", "example": "Garlic adds flavor to the sauce." },
      { "word": "grape", "meaning": "a small round fruit used fresh or for wine", "japaneseMeaning": "ぶどう", "synonyms": "fruit, berry", "antonyms": "", "example": "She picked a grape from the bunch." },
      { "word": "jam", "meaning": "fruit preserved with sugar, spread on bread", "japaneseMeaning": "ジャム", "synonyms": "preserve, spread", "antonyms": "", "example": "He spread strawberry jam on his toast." },
      { "word": "lemon", "meaning": "a sour yellow citrus fruit", "japaneseMeaning": "レモン", "synonyms": "citrus, lime (similar)", "antonyms": "", "example": "Add lemon juice to the dressing." },
      { "word": "lettuce", "meaning": "a leafy vegetable used in salads", "japaneseMeaning": "レタス", "synonyms": "greens, salad leaf", "antonyms": "", "example": "She tossed lettuce with tomatoes." },
      { "word": "mushroom", "meaning": "an edible fungus used in cooking", "japaneseMeaning": "きのこ", "synonyms": "fungus, toadstool", "antonyms": "", "example": "He added mushrooms to the pasta." },
      { "word": "onion", "meaning": "a layered vegetable with a strong flavor", "japaneseMeaning": "たまねぎ", "synonyms": "bulb, allium", "antonyms": "", "example": "She chopped an onion for the sauce." },
      { "word": "pepper", "meaning": "a spicy or sweet vegetable or spice", "japaneseMeaning": "ピーマン／胡椒", "synonyms": "capsicum, spice", "antonyms": "", "example": "Roast the pepper until it's soft." },
      { "word": "salad", "meaning": "a cold dish of mixed vegetables or fruit", "japaneseMeaning": "サラダ", "synonyms": "greens, side dish", "antonyms": "stew, soup", "example": "We had a fresh salad with lunch." },
      { "word": "sausage", "meaning": "ground meat seasoned and stuffed into casing", "japaneseMeaning": "ソーセージ", "synonyms": "link, frankfurter", "antonyms": "vegetarian patty", "example": "He grilled sausages for breakfast." },
      { "word": "soup", "meaning": "a liquid dish often containing vegetables or meat", "japaneseMeaning": "スープ", "synonyms": "broth, stew", "antonyms": "solid meal", "example": "Tomato soup warmed us up." },
      { "word": "spinach", "meaning": "a green leafy vegetable high in nutrients", "japaneseMeaning": "ほうれん草", "synonyms": "greens, leafy vegetable", "antonyms": "", "example": "She added spinach to the omelet." },
      { "word": "steak", "meaning": "a slice of meat, usually beef, cooked by grilling or frying", "japaneseMeaning": "ステーキ", "synonyms": "cut, filet", "antonyms": "vegetarian dish", "example": "He ordered a medium-rare steak." }
    ]
  }
  