  {
    "lesson_id": "eiken-1-80",
    "title": "Lesson 80",
    "paragraph": "This lesson focuses on work and effort, highlighting industrious, diligent, and meticulous traits.",
    "words": [
      {
        "word": "industrious",
        "meaning": "diligent and hardworking",
        "japaneseMeaning": "勤勉な、熱心な",
        "synonyms": "diligent, hardworking",
        "antonyms": "lazy, idle",
        "example": "She is an industrious student."
      },
      {
        "word": "diligent",
        "meaning": "showing care and conscientiousness in work",
        "japaneseMeaning": "勤勉な、熱心な",
        "synonyms": "assiduous, meticulous",
        "antonyms": "negligent, careless",
        "example": "He was diligent in completing his tasks."
      },
      {
        "word": "assiduous",
        "meaning": "showing great care and perseverance",
        "japaneseMeaning": "勤勉な、根気強い",
        "synonyms": "diligent, persistent",
        "antonyms": "lazy, inattentive",
        "example": "Her assiduous efforts paid off."
      },
      {
        "word": "meticulous",
        "meaning": "showing great attention to detail",
        "japaneseMeaning": "細心の注意を払った、几帳面な",
        "synonyms": "careful, precise",
        "antonyms": "careless, sloppy",
        "example": "He was meticulous in his research."
      },
      {
        "word": "conscientious",
        "meaning": "wishing to do what is right; thorough and responsible",
        "japaneseMeaning": "良心的な、誠実な",
        "synonyms": "dutiful, diligent",
        "antonyms": "careless, negligent",
        "example": "She is conscientious about her work."
      },
      {
        "word": "persevering",
        "meaning": "continuing in a course of action despite difficulty",
        "japaneseMeaning": "忍耐強い、根気のある",
        "synonyms": "persistent, determined",
        "antonyms": "quitting, lazy",
        "example": "He is persevering in his studies."
      },
      {
        "word": "dedicated",
        "meaning": "devoted to a task or purpose",
        "japaneseMeaning": "献身的な、熱心な",
        "synonyms": "committed, devoted",
        "antonyms": "apathetic, indifferent",
        "example": "She is dedicated to helping the community."
      },
      {
        "word": "methodical",
        "meaning": "done according to a systematic or established procedure",
        "japaneseMeaning": "体系的な、秩序立った",
        "synonyms": "organized, systematic",
        "antonyms": "chaotic, haphazard",
        "example": "He approached the task in a methodical way."
      },
      {
        "word": "systematic",
        "meaning": "done or acting according to a fixed plan or system",
        "japaneseMeaning": "体系的な、計画的な",
        "synonyms": "organized, methodical",
        "antonyms": "random, unplanned",
        "example": "They conducted a systematic review of the data."
      },
      {
        "word": "tireless",
        "meaning": "having or showing great effort or energy without getting tired",
        "japaneseMeaning": "疲れ知らずの、精力的な",
        "synonyms": "indefatigable, energetic",
        "antonyms": "lazy, fatigued",
        "example": "She worked tirelessly to complete the project."
      }
    ]
  }
 