 {
    "lesson_id": "eiken-2-48",
    "title": "Lesson 48",
    "paragraph": "Reason and purpose involve motivation, justification, and objectives. Understanding intentions, aims, functions, and principles guides action effectively.",
    "words": [
      {"word": "motivation", "meaning": "reason for acting", "japaneseMeaning": "動機", "synonyms": "drive, incentive", "antonyms": "apathy, indifference", "example": "His motivation led to success."},
      {"word": "justification", "meaning": "explanation or reason", "japaneseMeaning": "正当化", "synonyms": "defense, rationale", "antonyms": "condemnation, criticism", "example": "The justification was acceptable."},
      {"word": "rationale", "meaning": "underlying reason or basis", "japaneseMeaning": "根拠", "synonyms": "reasoning, explanation", "antonyms": "", "example": "The rationale was clear."},
      {"word": "objective", "meaning": "goal or aim", "japaneseMeaning": "目的", "synonyms": "goal, target", "antonyms": "aimlessness, randomness", "example": "The objective was achieved."},
      {"word": "intention", "meaning": "plan or purpose", "japaneseMeaning": "意図", "synonyms": "aim, purpose", "antonyms": "accident, chance", "example": "Her intention was honest."},
      {"word": "premise", "meaning": "basis for argument", "japaneseMeaning": "前提", "synonyms": "assumption, foundation", "antonyms": "", "example": "The premise was sound."},
      {"word": "purpose", "meaning": "reason for existence", "japaneseMeaning": "目的", "synonyms": "aim, intention", "antonyms": "pointlessness, futility", "example": "The purpose of the study is clear."},
      {"word": "aim", "meaning": "desired outcome", "japaneseMeaning": "狙い", "synonyms": "goal, objective", "antonyms": "randomness, accident", "example": "The aim was to improve quality."},
      {"word": "function", "meaning": "role or duty", "japaneseMeaning": "機能", "synonyms": "purpose, role", "antonyms": "", "example": "The function of the heart is vital."},
      {"word": "principle", "meaning": "fundamental truth or rule", "japaneseMeaning": "原理、原則", "synonyms": "rule, law", "antonyms": "unprincipledness, chaos", "example": "He follows strong principles."}
    ]
  }
 