 {
    "lesson_id": "eiken-2-7",
    "title": "Lesson 7",
    "paragraph": "Documents and procedural processes are essential for organized work. Acquiring, coding, declaring, and assuring proper records help achieve goals while overcoming barriers and managing resources efficiently.",
    "words": [
      { "word": "acquire", "meaning": "to gain or obtain something", "japaneseMeaning": "取得する、習得する", "synonyms": "obtain, procure", "antonyms": "lose, forfeit", "example": "She acquired new skills through training." },
      { "word": "code", "meaning": "to assign a system of symbols or rules for classification", "japaneseMeaning": "コード化する、符号化する", "synonyms": "cipher, classify", "antonyms": "decode, reveal", "example": "The documents were coded for confidentiality." },
      { "word": "ago", "meaning": "in the past", "japaneseMeaning": "以前に", "synonyms": "previously, earlier", "antonyms": "future, later", "example": "She moved to Tokyo ten years ago." },
      { "word": "assure", "meaning": "to make someone confident about something", "japaneseMeaning": "保証する、確信させる", "synonyms": "guarantee, promise", "antonyms": "doubt, unsettle", "example": "He assured her that everything would be fine." },
      { "word": "calendar", "meaning": "a system for organizing days for social, religious, or administrative purposes", "japaneseMeaning": "カレンダー、日程表", "synonyms": "schedule, timetable", "antonyms": "", "example": "We marked the holidays on the calendar." },
      { "word": "barrier", "meaning": "a physical or figurative obstacle", "japaneseMeaning": "障壁、壁", "synonyms": "obstacle, hurdle", "antonyms": "pathway, access", "example": "Language can be a barrier to communication." },
      { "word": "bargain", "meaning": "to negotiate a price or deal", "japaneseMeaning": "交渉する、掘り出し物", "synonyms": "negotiate, deal", "antonyms": "overpay, surrender", "example": "They bargained for a lower price at the market." },
      { "word": "fuel", "meaning": "to supply energy or power for something", "japaneseMeaning": "燃料を供給する、活気づける", "synonyms": "energize, power", "antonyms": "drain, weaken", "example": "The debate fueled public interest in the issue." },
      { "word": "achieve", "meaning": "to successfully reach a goal", "japaneseMeaning": "達成する", "synonyms": "attain, accomplish", "antonyms": "fail, miss", "example": "She achieved her dream of becoming a doctor." },
      { "word": "declare", "meaning": "to announce something officially", "japaneseMeaning": "宣言する、申告する", "synonyms": "announce, proclaim", "antonyms": "conceal, withhold", "example": "He declared his candidacy for mayor." }
    ]
  }
